pytubekit/__init__.py
pytubekit/client_secret.json
pytubekit/configs.py
pytubekit/constants.py
pytubekit/main.py
pytubekit/static.py
pytubekit/util.py
pytubekit/youtube.py
pytubekit-0.0.35.dist-info/METADATA
pytubekit-0.0.35.dist-info/WHEEL
pytubekit-0.0.35.dist-info/entry_points.txt
pytubekit-0.0.35.dist-info/licenses/LICENSE
pytubekit-0.0.35.dist-info/RECORD
