Metadata-Version: 2.4
Name: pytubekit
Version: 0.0.35
Summary: Pytubekit will allow you to perform operations in your youtube account en masse
Project-URL: Homepage, https://github.com/veltzer/pytubekit
Project-URL: Bug Tracker, https://github.com/veltzer/pytubekit/issues
Project-URL: Documentation, https://veltzer.github.io/pytubekit
Project-URL: Download, https://pypi.org/project/pytubekit/
Project-URL: Repository, https://github.com/veltzer/pytubekit
Author-email: Mark Veltzer <mark.veltzer@gmail.com>
Maintainer-email: Mark Veltzer <mark.veltzer@gmail.com>
License-Expression: MIT
License-File: LICENSE
Keywords: google,playlist,videos,youtube
Classifier: Development Status :: 4 - Beta
Classifier: Environment :: Console
Classifier: License :: OSI Approved :: MIT License
Classifier: Operating System :: OS Independent
Classifier: Programming Language :: Python
Classifier: Programming Language :: Python :: 3
Classifier: Programming Language :: Python :: 3 :: Only
Classifier: Programming Language :: Python :: 3.12
Classifier: Topic :: Utilities
Requires-Python: >=3.12
Requires-Dist: browsercookie
Requires-Dist: google-api-python-client
Requires-Dist: pygooglehelper
Requires-Dist: pylogconf
Requires-Dist: pytconf
Requires-Dist: youtube-dl
